pysuso/__init__.py
pysuso/boards.py
pysuso/exceptions.py
pysuso/solvers.py
pysuso-0.3.1.dist-info/METADATA
pysuso-0.3.1.dist-info/WHEEL
pysuso-0.3.1.dist-info/licenses/LICENSE
pysuso-0.3.1.dist-info/RECORD
