Metadata-Version: 2.3
Name: pysuso
Version: 0.3.1
Summary: Sudoku sovler written in Python
Project-URL: Home, https://mcneall.github.io/PySuSo/
Project-URL: Repository, https://github.com/McNeall/PySuSo
Project-URL: Documentation, https://mcneall.github.io/PySuSo/
Project-URL: pypi, https://pypi.org/project/pysuso
Author-email: Robert Schmidt <allthingscoding21th@gmail.com>
License: MIT
License-File: LICENSE
Requires-Python: >=3.12
Provides-Extra: docs
Requires-Dist: black>=24.3.0; extra == 'docs'
Requires-Dist: mike>=2.0.0; extra == 'docs'
Requires-Dist: mkdocs-material>=9.5.13; extra == 'docs'
Requires-Dist: mkdocs>=1.5.3; extra == 'docs'
Requires-Dist: mkdocstrings[python]>=0.24.1; extra == 'docs'
Requires-Dist: versioningit>=3.0.0; extra == 'docs'
Provides-Extra: test
Requires-Dist: pytest>=8.0.2; extra == 'test'
